<?xml version="1.0" encoding="UTF-8"?>
<MF0 version="1.1" packageUris="http://schema.mathworks.com/mf0/ci/19700101 http://schema.mathworks.com/mf0/sl_modelref_info/R2021b http://schema.mathworks.com/mf0/slexec_mm_sto/R2021b_202103041117">
  <ModelRefInfoRepo.ModelRefInfoRoot type="ModelRefInfoRepo.ModelRefInfoRoot" uuid="e4d0ac3d-65eb-47e1-9a82-6f5ad001581f">
    <childModelRefInfo type="ModelRefInfoRepo.ChildModelRefInfo" uuid="9f294989-4ea9-4f06-a00f-3e46d529797e">
      <modelName>MassSpringDamperModel</modelName>
      <modelPath>MassSpringDamperModel</modelPath>
    </childModelRefInfo>
    <dataTransferInfos>AAFJTQAAAAAOAAAAOAAAAAYAAAAIAAAAAgAAAAAAAAAFAAAACAAAAAAAAAABAAAAAQAAAAAAAAAFAAQAAQAAAAEAAAAAAAAA</dataTransferInfos>
    <defaultsCMapping>{&quot;Inports&quot;:&quot;{\&quot;Name\&quot;:\&quot;Default\&quot;,\&quot;Checksum\&quot;:\&quot;Default\&quot;,\&quot;PerInstancePropertiesChecksum\&quot;:\&quot;\&quot;,\&quot;MemorySectionName\&quot;:\&quot;\&quot;,\&quot;MemorySectionChecksum\&quot;:\&quot;\&quot;}&quot;,&quot;Outports&quot;:&quot;{\&quot;Name\&quot;:\&quot;Default\&quot;,\&quot;Checksum\&quot;:\&quot;Default\&quot;,\&quot;PerInstancePropertiesChecksum\&quot;:\&quot;\&quot;,\&quot;MemorySectionName\&quot;:\&quot;\&quot;,\&quot;MemorySectionChecksum\&quot;:\&quot;\&quot;}&quot;,&quot;ParameterArguments&quot;:&quot;{\&quot;Name\&quot;:\&quot;Default\&quot;,\&quot;Checksum\&quot;:\&quot;Default\&quot;,\&quot;PerInstancePropertiesChecksum\&quot;:\&quot;\&quot;,\&quot;MemorySectionName\&quot;:\&quot;None\&quot;,\&quot;MemorySectionChecksum\&quot;:\&quot;None\&quot;}&quot;,&quot;LocalParameters&quot;:&quot;{\&quot;Name\&quot;:\&quot;Default\&quot;,\&quot;Checksum\&quot;:\&quot;Default\&quot;,\&quot;PerInstancePropertiesChecksum\&quot;:\&quot;\&quot;,\&quot;MemorySectionName\&quot;:\&quot;\&quot;,\&quot;MemorySectionChecksum\&quot;:\&quot;\&quot;}&quot;,&quot;GlobalParameters&quot;:&quot;{\&quot;Name\&quot;:\&quot;Default\&quot;,\&quot;Checksum\&quot;:\&quot;Default\&quot;,\&quot;PerInstancePropertiesChecksum\&quot;:\&quot;\&quot;,\&quot;MemorySectionName\&quot;:\&quot;\&quot;,\&quot;MemorySectionChecksum\&quot;:\&quot;\&quot;}&quot;,&quot;InternalData&quot;:&quot;{\&quot;Name\&quot;:\&quot;Default\&quot;,\&quot;Checksum\&quot;:\&quot;Default\&quot;,\&quot;PerInstancePropertiesChecksum\&quot;:\&quot;\&quot;,\&quot;MemorySectionName\&quot;:\&quot;\&quot;,\&quot;MemorySectionChecksum\&quot;:\&quot;\&quot;}&quot;,&quot;SharedLocalDataStores&quot;:&quot;{\&quot;Name\&quot;:\&quot;Default\&quot;,\&quot;Checksum\&quot;:\&quot;Default\&quot;,\&quot;PerInstancePropertiesChecksum\&quot;:\&quot;\&quot;,\&quot;MemorySectionName\&quot;:\&quot;None\&quot;,\&quot;MemorySectionChecksum\&quot;:\&quot;None\&quot;}&quot;,&quot;GlobalDataStores&quot;:&quot;{\&quot;Name\&quot;:\&quot;Default\&quot;,\&quot;Checksum\&quot;:\&quot;Default\&quot;,\&quot;PerInstancePropertiesChecksum\&quot;:\&quot;\&quot;,\&quot;MemorySectionName\&quot;:\&quot;None\&quot;,\&quot;MemorySectionChecksum\&quot;:\&quot;None\&quot;}&quot;,&quot;Constants&quot;:&quot;{\&quot;Name\&quot;:\&quot;Default\&quot;,\&quot;Checksum\&quot;:\&quot;Default\&quot;,\&quot;PerInstancePropertiesChecksum\&quot;:\&quot;\&quot;,\&quot;MemorySectionName\&quot;:\&quot;\&quot;,\&quot;MemorySectionChecksum\&quot;:\&quot;\&quot;}&quot;,&quot;DataTransfers&quot;:&quot;{\&quot;Name\&quot;:\&quot;Default\&quot;,\&quot;Checksum\&quot;:\&quot;Default\&quot;,\&quot;PerInstancePropertiesChecksum\&quot;:\&quot;\&quot;,\&quot;MemorySectionName\&quot;:\&quot;None\&quot;,\&quot;MemorySectionChecksum\&quot;:\&quot;None\&quot;}&quot;,&quot;ModelData&quot;:&quot;{\&quot;Name\&quot;:\&quot;Default\&quot;,\&quot;Checksum\&quot;:\&quot;Default\&quot;,\&quot;PerInstancePropertiesChecksum\&quot;:\&quot;\&quot;,\&quot;MemorySectionName\&quot;:\&quot;None\&quot;,\&quot;MemorySectionChecksum\&quot;:\&quot;None\&quot;}&quot;,&quot;InitializeTerminate&quot;:&quot;{\&quot;Name\&quot;:\&quot;Default\&quot;,\&quot;Checksum\&quot;:\&quot;Default\&quot;,\&quot;PerInstancePropertiesChecksum\&quot;:\&quot;\&quot;,\&quot;MemorySectionName\&quot;:\&quot;\&quot;,\&quot;MemorySectionChecksum\&quot;:\&quot;\&quot;}&quot;,&quot;Execution&quot;:&quot;{\&quot;Name\&quot;:\&quot;Default\&quot;,\&quot;Checksum\&quot;:\&quot;Default\&quot;,\&quot;PerInstancePropertiesChecksum\&quot;:\&quot;\&quot;,\&quot;MemorySectionName\&quot;:\&quot;\&quot;,\&quot;MemorySectionChecksum\&quot;:\&quot;\&quot;}&quot;,&quot;SharedUtility&quot;:&quot;{\&quot;Name\&quot;:\&quot;Default\&quot;,\&quot;Checksum\&quot;:\&quot;Default\&quot;,\&quot;PerInstancePropertiesChecksum\&quot;:\&quot;\&quot;,\&quot;MemorySectionName\&quot;:\&quot;\&quot;,\&quot;MemorySectionChecksum\&quot;:\&quot;\&quot;}&quot;}</defaultsCMapping>
    <hasBwsAccessed>true</hasBwsAccessed>
    <hasBwsAccessedByAnyModel>true</hasBwsAccessedByAnyModel>
    <hasContinuousSampleTime>true</hasContinuousSampleTime>
    <hasNonVirtualParameterChangeEvents>true</hasNonVirtualParameterChangeEvents>
    <inports type="ModelRefInfoRepo.InportInformation" uuid="4afaeea2-3149-40b3-ae5c-8ad378e82161">
      <designMax>Inf</designMax>
      <designMin>-Inf</designMin>
      <indexType>2</indexType>
      <rateInfos type="ModelRefInfoRepo.RateInfo">
        <compiled>true</compiled>
        <period>0.0</period>
        <priority>40</priority>
        <rateIdx>0</rateIdx>
      </rateInfos>
      <resolvedSignalObject></resolvedSignalObject>
      <sigNameToEMVCEMap type="ModelRefInfoRepo.SigNameEMVCEInfo" uuid="1d0ad14c-b404-45ed-b9c7-b3f060ec624b"/>
    </inports>
    <isOrigInportVirtualBus>false</isOrigInportVirtualBus>
    <isOrigOutportVirtualBus>false</isOrigOutportVirtualBus>
    <isOrigOutportVirtualBus>false</isOrigOutportVirtualBus>
    <loggingSaveFormat>6</loggingSaveFormat>
    <massMatrixNzMax>2</massMatrixNzMax>
    <maxFreqHz>-1.0</maxFreqHz>
    <numCStateRecs>2</numCStateRecs>
    <numContinuousStates>2</numContinuousStates>
    <numDataInputPorts>1</numDataInputPorts>
    <numLoggableCStateRecs>2</numLoggableCStateRecs>
    <numLoggableJacobianDStates>0</numLoggableJacobianDStates>
    <origInportBusType></origInportBusType>
    <origOutportBusOutputAsStruct>false</origOutportBusOutputAsStruct>
    <origOutportBusOutputAsStruct>false</origOutportBusOutputAsStruct>
    <origOutportBusType></origOutportBusType>
    <origOutportBusType></origOutportBusType>
    <outports type="ModelRefInfoRepo.OutportInformation" uuid="19c4457b-f0ad-424e-afe5-ee228a4a7715">
      <designMax>Inf</designMax>
      <designMin>-Inf</designMin>
      <rateInfos type="ModelRefInfoRepo.RateInfo">
        <compiled>true</compiled>
        <period>0.0</period>
        <priority>40</priority>
        <rateIdx>0</rateIdx>
      </rateInfos>
      <resolvedSignalObject></resolvedSignalObject>
      <sigNameToEMVCEMap type="ModelRefInfoRepo.SigNameEMVCEInfo" uuid="b6a18253-1382-4221-9344-972fe2f06e98"/>
    </outports>
    <outports type="ModelRefInfoRepo.OutportInformation" uuid="b02a2545-7312-438a-87ac-bb02828f2a46">
      <designMax>Inf</designMax>
      <designMin>-Inf</designMin>
      <originalPortNumber>1</originalPortNumber>
      <rateInfos type="ModelRefInfoRepo.RateInfo">
        <compiled>true</compiled>
        <period>0.0</period>
        <priority>40</priority>
        <rateIdx>0</rateIdx>
      </rateInfos>
      <resolvedSignalObject></resolvedSignalObject>
      <sigNameToEMVCEMap type="ModelRefInfoRepo.SigNameEMVCEInfo" uuid="3ccf937b-c595-443d-83e4-e3401b418394"/>
    </outports>
    <runtimeNonFcnCallRateInfos type="ModelRefInfoRepo.RateInfo">
      <compiled>true</compiled>
      <period>0.0</period>
      <priority>40</priority>
      <rateIdx>0</rateIdx>
    </runtimeNonFcnCallRateInfos>
    <sampleTimeInheritanceRule>2</sampleTimeInheritanceRule>
    <solverStatusFlags>32781</solverStatusFlags>
    <timingAndTaskingRegistry>&lt;?xml version=&quot;1.0&quot;?&gt;
&lt;slexec_sto version=&quot;1.1&quot; packageUris=&quot;http://schema.mathworks.com/mf0/slexec_mm_sto/R2021b_202103041117&quot;&gt;
  &lt;sto.Registry type=&quot;sto.Registry&quot; uuid=&quot;92c86ba8-cdc9-406c-8ae9-424019632b8e&quot;&gt;
    &lt;clocks type=&quot;sto.Timer&quot; uuid=&quot;fc861489-863a-4106-8adb-0bf65bb553fc&quot;&gt;
      &lt;clockDomain type=&quot;sto.ClockDomain&quot; uuid=&quot;7c25ba28-1390-4dcb-966f-b85b32dcb6f1&quot;&gt;
        &lt;baseTaskID&gt;_task0&lt;/baseTaskID&gt;
        &lt;rates type=&quot;sto.Rate&quot; uuid=&quot;31d2165d-8b5c-4d49-a755-e2c5ef5a163a&quot;/&gt;
        &lt;rootTaskHierarchyElements type=&quot;sto.Task&quot; uuid=&quot;9463fdd1-c674-4d43-ad6e-3dabd170a5ed&quot;&gt;
          &lt;isExecutable&gt;true&lt;/isExecutable&gt;
          &lt;orderIndex&gt;1&lt;/orderIndex&gt;
          &lt;rates type=&quot;sto.Rate&quot; uuid=&quot;31d2165d-8b5c-4d49-a755-e2c5ef5a163a&quot;&gt;
            &lt;annotation&gt;Cont&lt;/annotation&gt;
            &lt;description&gt;Continuous&lt;/description&gt;
            &lt;eventSourceType&gt;UNSPECIFIED_EVENT_SOURCE&lt;/eventSourceType&gt;
            &lt;registry type=&quot;sto.Registry&quot; uuid=&quot;92c86ba8-cdc9-406c-8ae9-424019632b8e&quot;/&gt;
            &lt;taskId&gt;_task0&lt;/taskId&gt;
            &lt;rateSpec type=&quot;sto.RateSpec&quot; uuid=&quot;1e71e609-9f04-43c5-b72d-ac3acb7d4400&quot;/&gt;
          &lt;/rates&gt;
          &lt;elementType&gt;Task&lt;/elementType&gt;
          &lt;identifier&gt;_task0&lt;/identifier&gt;
          &lt;priority&gt;40&lt;/priority&gt;
        &lt;/rootTaskHierarchyElements&gt;
      &lt;/clockDomain&gt;
    &lt;/clocks&gt;
    &lt;clocks type=&quot;sto.Event&quot; uuid=&quot;c9374356-f5d4-4b7b-8610-243776c84964&quot;&gt;
      &lt;clientId&gt;ParameterChangeEvent&lt;/clientId&gt;
      &lt;eventType&gt;PARAMETER_CHANGE_EVENT&lt;/eventType&gt;
      &lt;cNum&gt;1&lt;/cNum&gt;
      &lt;clockType&gt;Event&lt;/clockType&gt;
      &lt;identifier&gt;ParameterChangeEvent&lt;/identifier&gt;
      &lt;specifiedTaskingMode&gt;ExplicitTasking&lt;/specifiedTaskingMode&gt;
      &lt;timeAdvanceMode&gt;None&lt;/timeAdvanceMode&gt;
      &lt;clockDomain type=&quot;sto.ClockDomain&quot; uuid=&quot;34dc3a04-3b18-4f42-92bc-bf74e754f8f4&quot;&gt;
        &lt;rates type=&quot;sto.Rate&quot; uuid=&quot;867049be-aa79-4d98-9121-d63587cd84b6&quot;/&gt;
        &lt;rootTaskHierarchyElements type=&quot;sto.Task&quot; uuid=&quot;b128a321-c271-491c-b751-aaed90f0303f&quot;&gt;
          &lt;isExecutable&gt;true&lt;/isExecutable&gt;
          &lt;isExplicit&gt;true&lt;/isExplicit&gt;
          &lt;rates type=&quot;sto.Rate&quot; uuid=&quot;867049be-aa79-4d98-9121-d63587cd84b6&quot;&gt;
            &lt;annotation&gt;Inf&lt;/annotation&gt;
            &lt;colorIndex&gt;6&lt;/colorIndex&gt;
            &lt;description&gt;Constant&lt;/description&gt;
            &lt;eventSourceType&gt;PARAMETER_CHANGE_EVENT&lt;/eventSourceType&gt;
            &lt;rateIDX&gt;1&lt;/rateIDX&gt;
            &lt;registry type=&quot;sto.Registry&quot; uuid=&quot;92c86ba8-cdc9-406c-8ae9-424019632b8e&quot;/&gt;
            &lt;stringID&gt;ParameterChangeEvent&lt;/stringID&gt;
            &lt;taskId&gt;ModelWideParameterChangeEvent&lt;/taskId&gt;
            &lt;rateSpec type=&quot;sto.RateSpec&quot; uuid=&quot;95454116-6f55-47f3-84f9-813aef882d23&quot;&gt;
              &lt;period&gt;Inf&lt;/period&gt;
              &lt;rateType&gt;ModelWideParameterChangeEvent&lt;/rateType&gt;
            &lt;/rateSpec&gt;
          &lt;/rates&gt;
          &lt;tNum&gt;1&lt;/tNum&gt;
          &lt;elementType&gt;Task&lt;/elementType&gt;
          &lt;identifier&gt;ModelWideParameterChangeEvent&lt;/identifier&gt;
          &lt;priority&gt;-1&lt;/priority&gt;
          &lt;schedulingClockID&gt;ParameterChangeEvent&lt;/schedulingClockID&gt;
        &lt;/rootTaskHierarchyElements&gt;
      &lt;/clockDomain&gt;
    &lt;/clocks&gt;
    &lt;executionSpec&gt;Undetermined&lt;/executionSpec&gt;
    &lt;hasUnknownEdges&gt;true&lt;/hasUnknownEdges&gt;
    &lt;taskDependencyGraph type=&quot;sto.SerializedTaskConnectionList&quot; uuid=&quot;dc86a395-e941-4038-a92b-12a37e017cce&quot;&gt;
      &lt;taskIdentifier&gt;_task0&lt;/taskIdentifier&gt;
    &lt;/taskDependencyGraph&gt;
    &lt;taskDependencyGraph type=&quot;sto.SerializedTaskConnectionList&quot; uuid=&quot;1d1adcf3-2760-4019-bbc6-d580fbbab120&quot;&gt;
      &lt;clockIdentifier&gt;ParameterChangeEvent&lt;/clockIdentifier&gt;
      &lt;serializedConnectionProperties type=&quot;sto.SerializedConnectionProperties&quot; uuid=&quot;3d6ff41b-2e41-46bd-bbb3-cb039c8ca8f1&quot;&gt;
        &lt;targetTaskIdentifier&gt;_task0&lt;/targetTaskIdentifier&gt;
      &lt;/serializedConnectionProperties&gt;
      &lt;taskIdentifier&gt;ModelWideParameterChangeEvent&lt;/taskIdentifier&gt;
    &lt;/taskDependencyGraph&gt;
    &lt;taskPriorityDirection&gt;HighNumberLast&lt;/taskPriorityDirection&gt;
    &lt;tasks type=&quot;sto.Task&quot; uuid=&quot;9463fdd1-c674-4d43-ad6e-3dabd170a5ed&quot;/&gt;
    &lt;tasks type=&quot;sto.Task&quot; uuid=&quot;b128a321-c271-491c-b751-aaed90f0303f&quot;/&gt;
  &lt;/sto.Registry&gt;
&lt;/slexec_sto&gt;</timingAndTaskingRegistry>
    <FMUBlockMap type="ModelRefInfoRepo.FMUBlockInfo" uuid="fe21a3ac-f40f-4399-a066-5259f8dd5b2a"/>
    <codeGenInfo type="ModelRefInfoRepo.CodeGenInformation" uuid="58dd3118-3111-4582-9f79-495ca1e4d968"/>
    <compiledVariantInfos type="ModelRefInfoRepo.CompiledVariantInfoMap" uuid="ece76afb-dce1-4864-a646-3204962c13f4"/>
    <configSettingsForConsistencyChecks type="ModelRefInfoRepo.ConfigSettingsForConsistencyChecks" uuid="5b6563c9-ff5f-47af-9fac-b05b350e21bb">
      <consistentOutportInitialization>true</consistentOutportInitialization>
      <frameDiagnosticSetting>2</frameDiagnosticSetting>
      <signalLoggingSaveFormat>2</signalLoggingSaveFormat>
      <simSIMDOptimization>1</simSIMDOptimization>
      <solverName>VariableStepAuto</solverName>
      <hardwareSettings type="ModelRefInfoRepo.HardwareSettings" uuid="902f75ba-ef92-4122-a620-85159d8a3472">
        <prodBitPerChar>8</prodBitPerChar>
        <prodBitPerDouble>64</prodBitPerDouble>
        <prodBitPerFloat>32</prodBitPerFloat>
        <prodBitPerInt>32</prodBitPerInt>
        <prodBitPerLong>32</prodBitPerLong>
        <prodBitPerLongLong>64</prodBitPerLongLong>
        <prodBitPerPointer>32</prodBitPerPointer>
        <prodBitPerPtrDiffT>32</prodBitPerPtrDiffT>
        <prodBitPerShort>16</prodBitPerShort>
        <prodBitPerSizeT>32</prodBitPerSizeT>
        <prodIntDivRoundTo>2</prodIntDivRoundTo>
        <prodLargestAtomicFloat>2</prodLargestAtomicFloat>
        <prodShiftRight>true</prodShiftRight>
        <prodWordSize>32</prodWordSize>
      </hardwareSettings>
    </configSettingsForConsistencyChecks>
    <controllableInputRatesMap type="ModelRefInfoRepo.VarTsUIDMap" uuid="8f8d881a-0225-4efe-8c55-6e5b0a92e9d6"/>
    <controllableOutputRatesMap type="ModelRefInfoRepo.VarTsUIDMap" uuid="a9d546f7-bb1e-445b-90e9-42924040223f"/>
    <dataPortGroup type="ModelRefInfoRepo.DataPortGroup" uuid="f542f643-c5e0-4848-9329-0f798b5729cd">
      <compDataInputPorts>0</compDataInputPorts>
      <compDataOutputPorts>0</compDataOutputPorts>
      <compDataOutputPorts>1</compDataOutputPorts>
      <dataInputPorts>0</dataInputPorts>
      <dataOutputPorts>0</dataOutputPorts>
      <dataOutputPorts>1</dataOutputPorts>
    </dataPortGroup>
    <expFcnUnconnectedDataPortGroup type="ModelRefInfoRepo.DataPortGroup" uuid="d0a0c7eb-3695-43ef-9f72-10669e89b171"/>
    <interfaceParameterInfo type="ModelRefInfoRepo.InterfaceParameterInfo" uuid="80cb7499-2e68-4ed4-82da-4cfe306ce600"/>
    <messageInfo type="ModelRefInfoRepo.MessageInformation" uuid="d3033fc1-37b1-467a-985e-d7a91774a919"/>
    <methodInfo type="ModelRefInfoRepo.MethodExistenceInfo" uuid="9406ea7e-c37b-44d9-82d0-d22821407cfb">
      <hasDerivMethod>true</hasDerivMethod>
      <hasForcingFunctionMethod>true</hasForcingFunctionMethod>
      <hasSystemInitializeMethod>true</hasSystemInitializeMethod>
      <hasSystemResetMethod>true</hasSystemResetMethod>
      <hasTerminateMethod>true</hasTerminateMethod>
      <hasUpdateMethod>true</hasUpdateMethod>
    </methodInfo>
    <periodicEventPortUnsupportedBlockInfo type="ModelRefInfoRepo.PeriodicEventPortUnsupportedBlockInfo" uuid="9c4cd4af-d065-4b55-8813-8cac925432d5"/>
    <portGroupsRequireSameRate type="ModelRefInfoRepo.PortGroupsRequireSameRate" uuid="d1043d40-7b8f-45bd-96e4-fca2fe5b917e">
      <DSMPortGroups type="ModelRefInfoRepo.NameToPortGroupIdxVectMap" uuid="d42f0d99-aeb1-42be-8d9b-93d3caa5b034"/>
      <GlobalDSMPortGroups type="ModelRefInfoRepo.NameToPortGroupIdxVectMap" uuid="39fb8302-a30c-41f4-bfe5-f6d2f627de63"/>
      <mergedPortGroups type="ModelRefInfoRepo.NameToPortGroupIdxVectMap" uuid="6f5ed9ff-7baf-4537-a404-6114e11a40d2"/>
    </portGroupsRequireSameRate>
    <rateBasedMdlGlobalDSMRateSpec type="ModelRefInfoRepo.GlobalDSMRateSpecMap" uuid="2e2e0fcf-fab8-4f18-837d-b09e613eb126"/>
    <rateSpecOfGlobalDSMAccessedByDescExpFcnMdlMap type="ModelRefInfoRepo.GlobalDSMRateSpecMap" uuid="ef29d59e-df1d-4f65-9944-d42d0bc32ebe"/>
    <rootBlockDiagramInterface type="ci.Model" uuid="aee35655-f900-45c0-80b8-8ff18b8d28e0">
      <p_RootComponentInterface type="ci.ComponentInterface" uuid="67dc8e5e-1de0-41fe-ad7a-c20a1efe6574">
        <p_InputPorts type="ci.SignalInterface" uuid="b6df99e2-325b-48e0-8a81-59e4da59c4e4">
          <p_ComputedNumericDimensions>1.0</p_ComputedNumericDimensions>
          <p_ComputedSampleTime>0.0</p_ComputedSampleTime>
          <p_ComputedSampleTime>0.0</p_ComputedSampleTime>
        </p_InputPorts>
        <p_Name>MassSpringDamperModel</p_Name>
        <p_OutputPorts type="ci.SignalInterface" uuid="2cb32f99-2477-4e64-a3f4-f08c4f10c9e9">
          <p_ComputedNumericDimensions>1.0</p_ComputedNumericDimensions>
          <p_ComputedSampleTime>0.0</p_ComputedSampleTime>
          <p_ComputedSampleTime>0.0</p_ComputedSampleTime>
        </p_OutputPorts>
        <p_OutputPorts type="ci.SignalInterface" uuid="bbc6e883-95e1-4520-ac12-98425a02577f">
          <p_ComputedNumericDimensions>1.0</p_ComputedNumericDimensions>
          <p_ComputedSampleTime>0.0</p_ComputedSampleTime>
          <p_ComputedSampleTime>0.0</p_ComputedSampleTime>
        </p_OutputPorts>
        <p_Type>ROOT</p_Type>
      </p_RootComponentInterface>
    </rootBlockDiagramInterface>
    <simulinkFunctions type="ModelRefInfoRepo.SimulinkFunctions" uuid="682aa79d-9f56-4014-a5b3-bfa9778eb70b">
      <compSimulinkFunctionCatalog></compSimulinkFunctionCatalog>
    </simulinkFunctions>
    <stateWriterToOwnerMap type="ModelRefInfoRepo.StateWriterInfo" uuid="ec11b626-a94d-4d5e-b9a4-da8bbef784dd"/>
    <stoClientDataRegistry type="sto.ClientDataRegistry" uuid="2c2b2fb6-f39d-4a27-88aa-438d1cde338a">
      <dataSets type="sto.ClientClockNamedDataSet" uuid="e6780439-262c-455b-8142-2df8f83231a8">
        <tag>sltpEvents</tag>
      </dataSets>
      <dataSets type="sto.ClientTaskHierarchyElementNamedDataSet" uuid="8fd9978c-438c-4c1b-93bd-14dbfc3ad0fc">
        <tag>sltpTaskGroups</tag>
      </dataSets>
      <dataSets type="sto.ClientTaskHierarchyElementNamedDataSet" uuid="d46c4e0c-a1f3-4dfe-9b40-cb078e9d9bde">
        <dSet type="ModelRefInfoRepo.SltpTaskData" uuid="cb2e4471-80f4-4aff-9e82-81036593ffb9"/>
        <tSet type="ModelRefInfoRepo.SltpTaskData" uuid="cb2e4471-80f4-4aff-9e82-81036593ffb9">
          <dataName>Cont</dataName>
          <linkedSet type="sto.ClientTaskHierarchyElementNamedDataSet" uuid="d46c4e0c-a1f3-4dfe-9b40-cb078e9d9bde"/>
          <id type="sto.TaskHierarchyElementId">
            <id>_task0</id>
          </id>
        </tSet>
        <tag>sltpTasks</tag>
      </dataSets>
    </stoClientDataRegistry>
    <varTsUIDMap type="ModelRefInfoRepo.VarTsUIDMap" uuid="33af98ac-1d36-41ec-b168-3f8673b6d7b3"/>
  </ModelRefInfoRepo.ModelRefInfoRoot>
</MF0>